chandlerbot/bot.py
chandlerbot/config.py
chandlerbot/constants.py
chandlerbot/data_handlers.py
chandlerbot/errors.py
chandlerbot/input_error.py
chandlerbot/controllers/__init__.py
chandlerbot/controllers/adder.py
chandlerbot/controllers/deleter.py
chandlerbot/controllers/editor.py
chandlerbot/helpers/countries.py
chandlerbot/helpers/inputs.py
chandlerbot/helpers/location.py
chandlerbot/helpers/patterns.py
chandlerbot/helpers/session.py
chandlerbot/helpers/table_output.py
chandlerbot/helpers/ui.py
chandlerbot/helpers/validators.py
chandlerbot/helpers/weather.py
chandlerbot/input_handlers/__init__.py
chandlerbot/input_handlers/add_address.py
chandlerbot/input_handlers/add_birthday.py
chandlerbot/input_handlers/add_contact.py
chandlerbot/input_handlers/add_email.py
chandlerbot/input_handlers/add_note.py
chandlerbot/input_handlers/add_phone.py
chandlerbot/input_handlers/add_tag.py
chandlerbot/input_handlers/all_contacts.py
chandlerbot/input_handlers/birthdays.py
chandlerbot/input_handlers/change_contact.py
chandlerbot/input_handlers/delete_note.py
chandlerbot/input_handlers/edit_note.py
chandlerbot/input_handlers/edit_phone.py
chandlerbot/input_handlers/remove_address.py
chandlerbot/input_handlers/remove_birthday.py
chandlerbot/input_handlers/remove_contact.py
chandlerbot/input_handlers/remove_email.py
chandlerbot/input_handlers/remove_phone.py
chandlerbot/input_handlers/search_contact.py
chandlerbot/input_handlers/search_note.py
chandlerbot/input_handlers/select_contact.py
chandlerbot/input_handlers/show_address.py
chandlerbot/input_handlers/show_all_notes.py
chandlerbot/input_handlers/show_birthday.py
chandlerbot/input_handlers/show_contact.py
chandlerbot/input_handlers/show_note.py
chandlerbot/input_handlers/sort_notes_by_tag.py
chandlerbot/models/__init__.py
chandlerbot/models/address.py
chandlerbot/models/address_book.py
chandlerbot/models/birthday.py
chandlerbot/models/email.py
chandlerbot/models/field.py
chandlerbot/models/name.py
chandlerbot/models/note.py
chandlerbot-1.1.dist-info/METADATA
chandlerbot-1.1.dist-info/WHEEL
chandlerbot-1.1.dist-info/entry_points.txt
chandlerbot-1.1.dist-info/top_level.txt
chandlerbot-1.1.dist-info/RECORD
