Metadata-Version: 2.1
Name: chandlerbot
Version: 1.1
Summary: You personal assistant
Home-page: https://github.com/MKuzich/bot
Author: MKuzich
Author-email: chandlerbot@gmail.com
License: MIT
Requires-Dist: markdown
Requires-Dist: prompt-toolkit
Requires-Dist: pycountry
Requires-Dist: Pygments
Requires-Dist: tabulate
Requires-Dist: wcwidth
Requires-Dist: requests
